[
  {
    "epoch": 1,
    "loss": 0.6941206753253937,
    "auc": 0.5309487569761543,
    "f1": 0.15384615384615385,
    "tp": 5,
    "fp": 6,
    "fn": 49,
    "tn": 67,
    "thresholds": {
      "0.3": {
        "f1": 0.5966850828729282,
        "precision": 0.4251968503937008,
        "recall": 1.0,
        "tp": 54,
        "fp": 73,
        "fn": 0,
        "tn": 0
      },
      "0.5": {
        "f1": 0.15384615384615385,
        "precision": 0.45454545454545453,
        "recall": 0.09259259259259259,
        "tp": 5,
        "fp": 6,
        "fn": 49,
        "tn": 67
      },
      "0.7": {
        "f1": 0.0,
        "precision": 0.0,
        "recall": 0.0,
        "tp": 0,
        "fp": 0,
        "fn": 54,
        "tn": 73
      }
    },
    "comb": 0.3301467431604418
  },
  {
    "epoch": 2,
    "loss": 0.6765415718158087,
    "auc": 0.5636732623033993,
    "f1": 0.03508771929824561,
    "tp": 1,
    "fp": 2,
    "fn": 53,
    "tn": 71,
    "thresholds": {
      "0.3": {
        "f1": 0.5966850828729282,
        "precision": 0.4251968503937008,
        "recall": 1.0,
        "tp": 54,
        "fp": 73,
        "fn": 0,
        "tn": 0
      },
      "0.5": {
        "f1": 0.03508771929824561,
        "precision": 0.3333333333333333,
        "recall": 0.018518518518518517,
        "tp": 1,
        "fp": 2,
        "fn": 53,
        "tn": 71
      },
      "0.7": {
        "f1": 0.0,
        "precision": 0.0,
        "recall": 0.0,
        "tp": 0,
        "fp": 0,
        "fn": 54,
        "tn": 73
      }
    },
    "comb": 0.296066650644877
  },
  {
    "epoch": 3,
    "loss": 0.6612281733089023,
    "auc": 0.5654490106544902,
    "f1": 0.03571428571428571,
    "tp": 1,
    "fp": 1,
    "fn": 53,
    "tn": 72,
    "thresholds": {
      "0.3": {
        "f1": 0.5921787709497207,
        "precision": 0.424,
        "recall": 0.9814814814814815,
        "tp": 53,
        "fp": 72,
        "fn": 1,
        "tn": 1
      },
      "0.5": {
        "f1": 0.03571428571428571,
        "precision": 0.5,
        "recall": 0.018518518518518517,
        "tp": 1,
        "fp": 1,
        "fn": 53,
        "tn": 72
      },
      "0.7": {
        "f1": 0.0,
        "precision": 0.0,
        "recall": 0.0,
        "tp": 0,
        "fp": 0,
        "fn": 54,
        "tn": 73
      }
    },
    "comb": 0.2971424947452345
  },
  {
    "epoch": 4,
    "loss": 0.647616015540229,
    "auc": 0.5591070522577373,
    "f1": 0.13333333333333333,
    "tp": 4,
    "fp": 2,
    "fn": 50,
    "tn": 71,
    "thresholds": {
      "0.3": {
        "f1": 0.5813953488372093,
        "precision": 0.423728813559322,
        "recall": 0.9259259259259259,
        "tp": 50,
        "fp": 68,
        "fn": 4,
        "tn": 5
      },
      "0.5": {
        "f1": 0.13333333333333333,
        "precision": 0.6666666666666666,
        "recall": 0.07407407407407407,
        "tp": 4,
        "fp": 2,
        "fn": 50,
        "tn": 71
      },
      "0.7": {
        "f1": 0.0,
        "precision": 0.0,
        "recall": 0.0,
        "tp": 0,
        "fp": 0,
        "fn": 54,
        "tn": 73
      }
    },
    "comb": 0.33436834094368345
  },
  {
    "epoch": 5,
    "loss": 0.6375959681140052,
    "auc": 0.559107052257737,
    "f1": 0.2153846153846154,
    "tp": 7,
    "fp": 4,
    "fn": 47,
    "tn": 69,
    "thresholds": {
      "0.3": {
        "f1": 0.5764705882352941,
        "precision": 0.4224137931034483,
        "recall": 0.9074074074074074,
        "tp": 49,
        "fp": 67,
        "fn": 5,
        "tn": 6
      },
      "0.5": {
        "f1": 0.2153846153846154,
        "precision": 0.6363636363636364,
        "recall": 0.12962962962962962,
        "tp": 7,
        "fp": 4,
        "fn": 47,
        "tn": 69
      },
      "0.7": {
        "f1": 0.0,
        "precision": 0.0,
        "recall": 0.0,
        "tp": 0,
        "fp": 0,
        "fn": 54,
        "tn": 73
      }
    },
    "comb": 0.37009483667017906
  },
  {
    "epoch": 6,
    "loss": 0.626067739393976,
    "auc": 0.5553018772196855,
    "f1": 0.2608695652173913,
    "tp": 9,
    "fp": 6,
    "fn": 45,
    "tn": 67,
    "thresholds": {
      "0.3": {
        "f1": 0.5714285714285714,
        "precision": 0.42990654205607476,
        "recall": 0.8518518518518519,
        "tp": 46,
        "fp": 61,
        "fn": 8,
        "tn": 12
      },
      "0.5": {
        "f1": 0.2608695652173913,
        "precision": 0.6,
        "recall": 0.16666666666666666,
        "tp": 9,
        "fp": 6,
        "fn": 45,
        "tn": 67
      },
      "0.7": {
        "f1": 0.0,
        "precision": 0.0,
        "recall": 0.0,
        "tp": 0,
        "fp": 0,
        "fn": 54,
        "tn": 73
      }
    },
    "comb": 0.38924514150839346
  },
  {
    "epoch": 7,
    "loss": 0.6133382154835595,
    "auc": 0.5502283105022832,
    "f1": 0.3,
    "tp": 12,
    "fp": 14,
    "fn": 42,
    "tn": 59,
    "thresholds": {
      "0.3": {
        "f1": 0.5605095541401274,
        "precision": 0.42718446601941745,
        "recall": 0.8148148148148148,
        "tp": 44,
        "fp": 59,
        "fn": 10,
        "tn": 14
      },
      "0.5": {
        "f1": 0.3,
        "precision": 0.46153846153846156,
        "recall": 0.2222222222222222,
        "tp": 12,
        "fp": 14,
        "fn": 42,
        "tn": 59
      },
      "0.7": {
        "f1": 0.0,
        "precision": 0.0,
        "recall": 0.0,
        "tp": 0,
        "fp": 0,
        "fn": 54,
        "tn": 73
      }
    },
    "comb": 0.409558599695586
  },
  {
    "epoch": 8,
    "loss": 0.5976008193360435,
    "auc": 0.5385591070522577,
    "f1": 0.391304347826087,
    "tp": 18,
    "fp": 20,
    "fn": 36,
    "tn": 53,
    "thresholds": {
      "0.3": {
        "f1": 0.543046357615894,
        "precision": 0.422680412371134,
        "recall": 0.7592592592592593,
        "tp": 41,
        "fp": 56,
        "fn": 13,
        "tn": 17
      },
      "0.5": {
        "f1": 0.391304347826087,
        "precision": 0.47368421052631576,
        "recall": 0.3333333333333333,
        "tp": 18,
        "fp": 20,
        "fn": 36,
        "tn": 53
      },
      "0.7": {
        "f1": 0.0,
        "precision": 0.0,
        "recall": 0.0,
        "tp": 0,
        "fp": 0,
        "fn": 54,
        "tn": 73
      }
    },
    "comb": 0.4533375245406216
  },
  {
    "epoch": 9,
    "loss": 0.5717131992181143,
    "auc": 0.54337899543379,
    "f1": 0.48695652173913045,
    "tp": 28,
    "fp": 33,
    "fn": 26,
    "tn": 40,
    "thresholds": {
      "0.3": {
        "f1": 0.569620253164557,
        "precision": 0.4326923076923077,
        "recall": 0.8333333333333334,
        "tp": 45,
        "fp": 59,
        "fn": 9,
        "tn": 14
      },
      "0.5": {
        "f1": 0.48695652173913045,
        "precision": 0.45901639344262296,
        "recall": 0.5185185185185185,
        "tp": 28,
        "fp": 33,
        "fn": 26,
        "tn": 40
      },
      "0.7": {
        "f1": 0.07017543859649122,
        "precision": 0.6666666666666666,
        "recall": 0.037037037037037035,
        "tp": 2,
        "fp": 1,
        "fn": 52,
        "tn": 72
      }
    },
    "comb": 0.5214801579423378
  },
  {
    "epoch": 10,
    "loss": 0.5410586976342731,
    "auc": 0.5200405885337391,
    "f1": 0.4716981132075472,
    "tp": 25,
    "fp": 27,
    "fn": 29,
    "tn": 46,
    "thresholds": {
      "0.3": {
        "f1": 0.5034965034965035,
        "precision": 0.4044943820224719,
        "recall": 0.6666666666666666,
        "tp": 36,
        "fp": 53,
        "fn": 18,
        "tn": 20
      },
      "0.5": {
        "f1": 0.4716981132075472,
        "precision": 0.4807692307692308,
        "recall": 0.46296296296296297,
        "tp": 25,
        "fp": 27,
        "fn": 29,
        "tn": 46
      },
      "0.7": {
        "f1": 0.06779661016949153,
        "precision": 0.4,
        "recall": 0.037037037037037035,
        "tp": 2,
        "fp": 3,
        "fn": 52,
        "tn": 70
      }
    },
    "comb": 0.4941223208217263
  },
  {
    "epoch": 11,
    "loss": 0.500354577269819,
    "auc": 0.5208016235413495,
    "f1": 0.43636363636363634,
    "tp": 24,
    "fp": 32,
    "fn": 30,
    "tn": 41,
    "thresholds": {
      "0.3": {
        "f1": 0.5035971223021583,
        "precision": 0.4117647058823529,
        "recall": 0.6481481481481481,
        "tp": 35,
        "fp": 50,
        "fn": 19,
        "tn": 23
      },
      "0.5": {
        "f1": 0.43636363636363634,
        "precision": 0.42857142857142855,
        "recall": 0.4444444444444444,
        "tp": 24,
        "fp": 32,
        "fn": 30,
        "tn": 41
      },
      "0.7": {
        "f1": 0.12698412698412698,
        "precision": 0.4444444444444444,
        "recall": 0.07407407407407407,
        "tp": 4,
        "fp": 5,
        "fn": 50,
        "tn": 68
      }
    },
    "comb": 0.4801987915686545
  },
  {
    "epoch": 12,
    "loss": 0.4546377095911238,
    "auc": 0.4984779299847793,
    "f1": 0.4297520661157025,
    "tp": 26,
    "fp": 41,
    "fn": 28,
    "tn": 32,
    "thresholds": {
      "0.3": {
        "f1": 0.4748201438848921,
        "precision": 0.38823529411764707,
        "recall": 0.6111111111111112,
        "tp": 33,
        "fp": 52,
        "fn": 21,
        "tn": 21
      },
      "0.5": {
        "f1": 0.4297520661157025,
        "precision": 0.3880597014925373,
        "recall": 0.48148148148148145,
        "tp": 26,
        "fp": 41,
        "fn": 28,
        "tn": 32
      },
      "0.7": {
        "f1": 0.2857142857142857,
        "precision": 0.4782608695652174,
        "recall": 0.2037037037037037,
        "tp": 11,
        "fp": 12,
        "fn": 43,
        "tn": 61
      }
    },
    "comb": 0.4744608811233967
  }
]